exceptiongroups.py
exceptiongroups-0.0.0a0.dist-info/LICENSE
exceptiongroups-0.0.0a0.dist-info/WHEEL
exceptiongroups-0.0.0a0.dist-info/METADATA
exceptiongroups-0.0.0a0.dist-info/RECORD
