Metadata-Version: 2.1
Name: exceptiongroups
Version: 0.0.0a0
Summary: did you mean exceptiongroup - without an s?
Author-email: Thomas Grainger <exceptiongroup@graingert.co.uk>
Classifier: License :: OSI Approved :: MIT License
Requires-Dist: exceptiongroup
Project-URL: Home, https://pypi.org/project/exceptiongroup/
